hatano/__init__.py
hatano/acm.py
hatano/actions.py
hatano/apigateway.py
hatano/clean.py
hatano/cloudfront.py
hatano/conduct.py
hatano/errors.py
hatano/iam.py
hatano/lmbda.py
hatano/route53.py
hatano/s3.py
hatano/util.py
hatano-1.0.4.dist-info/LICENSE.md
hatano-1.0.4.dist-info/METADATA
hatano-1.0.4.dist-info/WHEEL
hatano-1.0.4.dist-info/entry_points.txt
hatano-1.0.4.dist-info/top_level.txt
hatano-1.0.4.dist-info/RECORD
