Metadata-Version: 2.1
Name: hatano
Version: 1.0.4
Summary: Microframework for Lambda/API gateway
Home-page: https://github.com/tripleko-llc/hatano
Author: Tripleko LLC
Author-email: jared@tripleko.com
License: UNKNOWN
Platform: UNKNOWN
Classifier: Programming Language :: Python :: 3
Classifier: License :: OSI Approved :: MIT License
Classifier: Operating System :: OS Independent
Requires-Dist: boto3
